ddexreader/ddexreader.py
ddexreader/__init__.py
ddexreader/ern312/binding.py
ddexreader/ern312/_ddex.py
ddexreader/ern312/_ddexC.py
ddexreader/ern312/_iso3166a2.py
ddexreader/ern312/_iso4217a.py
ddexreader/ern312/_iso639a2.py
ddexreader/ern312/__init__.py
ddexreader/ern32/binding.py
ddexreader/ern32/_ddex.py
ddexreader/ern32/_ddexC.py
ddexreader/ern32/_iso3166a2.py
ddexreader/ern32/_iso4217a.py
ddexreader/ern32/_iso639a2.py
ddexreader/ern32/__init__.py
ddexreader/ern33/binding.py
ddexreader/ern33/_ddex.py
ddexreader/ern33/_ddexC.py
ddexreader/ern33/_iso3166a2.py
ddexreader/ern33/_iso4217a.py
ddexreader/ern33/_iso639a2.py
ddexreader/ern33/__init__.py
ddexreader/ern34/binding.py
ddexreader/ern34/_ddex.py
ddexreader/ern34/_ddexC.py
ddexreader/ern34/_iso3166a2.py
ddexreader/ern34/_iso4217a.py
ddexreader/ern34/_iso639a2.py
ddexreader/ern34/__init__.py
ddexreader/ern341/binding.py
ddexreader/ern341/_ddex.py
ddexreader/ern341/_ddexC.py
ddexreader/ern341/_iso3166a2.py
ddexreader/ern341/_iso4217a.py
ddexreader/ern341/_iso639a2.py
ddexreader/ern341/__init__.py
ddexreader/ern35/binding.py
ddexreader/ern35/_ddex.py
ddexreader/ern35/_ddexC.py
ddexreader/ern35/_iso3166a2.py
ddexreader/ern35/_iso4217a.py
ddexreader/ern35/_iso639a2.py
ddexreader/ern35/__init__.py
ddexreader/ern351/binding.py
ddexreader/ern351/_ddex.py
ddexreader/ern351/_ddexC.py
ddexreader/ern351/_iso3166a2.py
ddexreader/ern351/_iso4217a.py
ddexreader/ern351/_iso639a2.py
ddexreader/ern351/__init__.py
ddexreader/ern36/binding.py
ddexreader/ern36/_avs.py
ddexreader/ern36/__init__.py
ddexreader-0.1.1.dist-info/DESCRIPTION.rst
ddexreader-0.1.1.dist-info/METADATA
ddexreader-0.1.1.dist-info/metadata.json
ddexreader-0.1.1.dist-info/pbr.json
ddexreader-0.1.1.dist-info/RECORD
ddexreader-0.1.1.dist-info/top_level.txt
ddexreader-0.1.1.dist-info/WHEEL
