Metadata-Version: 2.0
Name: ddexreader
Version: 0.1.1
Summary: This small project allows you to decode DDEX files into friendly Python data types.
Home-page: https://github.com/Trax-air/ddexreader
Author: Flavian Hautbois
Author-email: flavian@trax-air.com
License: MIT
Keywords: ddexreader
Platform: UNKNOWN
Classifier: Development Status :: 4 - Beta
Classifier: Intended Audience :: Developers
Classifier: License :: OSI Approved :: MIT License
Classifier: Natural Language :: English
Classifier: Programming Language :: Python :: 2
Classifier: Programming Language :: Python :: 2.6
Classifier: Programming Language :: Python :: 2.7
Requires-Dist: PyXB
